tbsync/__init__.py
tbsync/__main__.py
tbsync/client.py
tbsync/entry.py
tbsync/config/__init__.py
tbsync/config/meta.py
tbsync/operate/__init__.py
tbsync/operate/init.py
tbsync/operate/upload.py
tbsync/template/.gitattributes
tbsync/template/.gitignore
tbsync/template/Dockerfile
tbsync/template/README.md
tbsync/template/__init__.py
tbsync/template/requirements.txt
tbsync/utils/__init__.py
tbsync/utils/cli.py
tbsync-0.0.1.dist-info/LICENSE
tbsync-0.0.1.dist-info/METADATA
tbsync-0.0.1.dist-info/WHEEL
tbsync-0.0.1.dist-info/entry_points.txt
tbsync-0.0.1.dist-info/top_level.txt
tbsync-0.0.1.dist-info/RECORD
