Metadata-Version: 2.1
Name: tbsync
Version: 0.0.1
Summary: Sync tools for tensorboard logs.
Home-page: https://github.com/deepghs/tbsync
Author: narugo1992
Author-email: narugo@126.com
License: Apache License, Version 2.0
Keywords: python,tensorboard,huggingface
Classifier: Development Status :: 5 - Production/Stable
Classifier: Intended Audience :: Developers
Classifier: License :: OSI Approved :: Apache Software License
Classifier: Programming Language :: Python
Classifier: Programming Language :: Python :: 3
Classifier: Programming Language :: Python :: 3.7
Classifier: Programming Language :: Python :: 3.8
Classifier: Programming Language :: Python :: 3.9
Classifier: Programming Language :: Python :: 3.10
Classifier: Programming Language :: Python :: 3.11
Requires-Python: >=3.7
License-File: LICENSE
Requires-Dist: hbutils (>=0.9.0)
Requires-Dist: huggingface-hub (>=0.14.0)
Requires-Dist: tensorboard
Requires-Dist: click (>=7.0.0)
Requires-Dist: emoji
Requires-Dist: di-toolkit
Requires-Dist: typing-extensions ; python_version < "3.10"
Provides-Extra: doc
Requires-Dist: Jinja2 (~=3.0.0) ; extra == 'doc'
Requires-Dist: sphinx (~=3.2.0) ; extra == 'doc'
Requires-Dist: sphinx-rtd-theme (~=0.4.3) ; extra == 'doc'
Requires-Dist: enum-tools ; extra == 'doc'
Requires-Dist: sphinx-toolbox ; extra == 'doc'
Requires-Dist: plantumlcli (>=0.0.2) ; extra == 'doc'
Requires-Dist: packaging ; extra == 'doc'
Requires-Dist: sphinx-multiversion (~=0.2.4) ; extra == 'doc'
Requires-Dist: where (~=1.0.2) ; extra == 'doc'
Requires-Dist: easydict (<2,>=1.7) ; extra == 'doc'
Requires-Dist: responses (>=0.20.0) ; extra == 'doc'
Requires-Dist: matplotlib ; extra == 'doc'
Requires-Dist: natsort ; extra == 'doc'
Requires-Dist: nbsphinx (>=0.8.8) ; extra == 'doc'
Requires-Dist: ipython (>=7.16.3) ; extra == 'doc'
Requires-Dist: psutil (>=5.8.0) ; extra == 'doc'
Requires-Dist: ipykernel (>=6.15) ; extra == 'doc'
Requires-Dist: py-cpuinfo (>=8.0.0) ; extra == 'doc'
Requires-Dist: click (>=7.0.0) ; extra == 'doc'
Provides-Extra: test
Requires-Dist: coverage (>=5) ; extra == 'test'
Requires-Dist: mock (>=4.0.3) ; extra == 'test'
Requires-Dist: flake8 (~=3.5) ; extra == 'test'
Requires-Dist: testfixtures (>=6.18.5) ; extra == 'test'
Requires-Dist: pytest (~=6.2.5) ; extra == 'test'
Requires-Dist: pytest-cov (~=3.0.0) ; extra == 'test'
Requires-Dist: pytest-mock (~=3.6.1) ; extra == 'test'
Requires-Dist: pytest-xdist (>=1.34.0) ; extra == 'test'
Requires-Dist: pytest-rerunfailures (~=10.2) ; extra == 'test'
Requires-Dist: pytest-timeout (~=2.0.2) ; extra == 'test'
Requires-Dist: pytest-benchmark (~=3.4.0) ; extra == 'test'
Requires-Dist: easydict (<2,>=1.7) ; extra == 'test'
Requires-Dist: testtools (>=2) ; extra == 'test'
Requires-Dist: where (>=1.0.2) ; extra == 'test'
Requires-Dist: responses (>=0.20.0) ; extra == 'test'
Requires-Dist: pytest-image-diff (>=0.0.11) ; extra == 'test'
Requires-Dist: matplotlib ; extra == 'test'
